.gitignore
Jenkinsfile
MANIFEST.in
README.md
requirements.txt
setup.py
tox.ini
docs/Makefile
docs/conf.py
docs/index.rst
docs/modules.rst
docs/setup.rst
docs/sky.rst
docs/sky.utils.rst
docs/tests.rst
resources/requirements/base.txt
resources/requirements/dev.txt
resources/requirements/prod.txt
sky/__init__.py
sky/utils/__init__.py
sky/utils/__version__.py
sky/utils/attr_dict.py
sky/utils/attr_lookup.py
sky/utils/base.py
sky/utils/cls.py
sky/utils/crypto.py
sky/utils/date.py
sky/utils/date_utils.py
sky/utils/file.py
sky/utils/file_utils.py
sky/utils/registry.py
sky/utils/string_prettier.py
sky/utils/text.py
sky/utils/xml.py
sky/utils/client/__init__.py
sky/utils/client/http/__init__.py
sky/utils/client/http/base.py
sky/utils/client/http/exc.py
sky/utils/client/http/failover.py
sky/utils/client/http/status.py
sky/utils/client/http/utils.py
sky/utils/client/ssh/__init__.py
sky/utils/client/ssh/sshparamiko.py
sky_utils.egg-info/PKG-INFO
sky_utils.egg-info/SOURCES.txt
sky_utils.egg-info/dependency_links.txt
sky_utils.egg-info/requires.txt
sky_utils.egg-info/top_level.txt
tests/__init__.py
tests/test_attr_dict.py
tests/test_base_util.py
tests/test_date_utils.py
tests/test_file_utils.py
tests/test_text_util.py