Metadata-Version: 1.0
Name: sky-utils
Version: 1.0a1.dev2
Summary: Sky Utils
Home-page: https://bitbucket.org/sekomy/skypy-utils
Author: Sekom Yazilim
Author-email: info@sekomyazilim.com.tr
License: MIT
Platform: UNKNOWN
